CHANGELOG.md
sane_out/__init__.py
sane_out/colour.py
sane_out/printer.py
sane_out-0.2.1.dist-info/LICENSE
sane_out-0.2.1.dist-info/WHEEL
sane_out-0.2.1.dist-info/METADATA
sane_out-0.2.1.dist-info/RECORD
