Metadata-Version: 2.1
Name: sane-out
Version: 0.2.1
Summary: A lightweight library for clean console output
Home-page: https://github.com/sane-out/python
License: MIT
Keywords: console output,cli,sane-out
Author: Nikita Karamov
Author-email: nick@karamoff.dev
Requires-Python: >=3.5,<4.0
Classifier: Development Status :: 1 - Planning
Classifier: License :: OSI Approved :: MIT License
Classifier: Operating System :: OS Independent
Classifier: Programming Language :: Python :: 3
Classifier: Programming Language :: Python :: 3 :: Only
Classifier: Programming Language :: Python :: 3.10
Classifier: Programming Language :: Python :: 3.5
Classifier: Programming Language :: Python :: 3.6
Classifier: Programming Language :: Python :: 3.7
Classifier: Programming Language :: Python :: 3.8
Classifier: Programming Language :: Python :: 3.9
Classifier: Topic :: Software Development :: Libraries
Classifier: Topic :: System :: Logging
Classifier: Typing :: Typed
Requires-Dist: colorama (>=0.4.4,<0.5.0); sys_platform == "win32"
Project-URL: Repository, https://github.com/sane-out/python
